[
  {
    "url": "https://api.github.com/repos/elswork/anticitera.deft.work/issues/1",
    "repository_url": "https://api.github.com/repos/elswork/anticitera.deft.work",
    "labels_url": "https://api.github.com/repos/elswork/anticitera.deft.work/issues/1/labels{/name}",
    "comments_url": "https://api.github.com/repos/elswork/anticitera.deft.work/issues/1/comments",
    "events_url": "https://api.github.com/repos/elswork/anticitera.deft.work/issues/1/events",
    "html_url": "https://github.com/elswork/anticitera.deft.work/issues/1",
    "id": 2010752239,
    "node_id": "I_kwDOKvKGl8532aTv",
    "number": 1,
    "title": "Comentario de prueba",
    "user": {
      "login": "elswork",
      "id": 1455507,
      "node_id": "MDQ6VXNlcjE0NTU1MDc=",
      "avatar_url": "https://avatars.githubusercontent.com/u/1455507?v=4",
      "gravatar_id": "",
      "url": "https://api.github.com/users/elswork",
      "html_url": "https://github.com/elswork",
      "followers_url": "https://api.github.com/users/elswork/followers",
      "following_url": "https://api.github.com/users/elswork/following{/other_user}",
      "gists_url": "https://api.github.com/users/elswork/gists{/gist_id}",
      "starred_url": "https://api.github.com/users/elswork/starred{/owner}{/repo}",
      "subscriptions_url": "https://api.github.com/users/elswork/subscriptions",
      "organizations_url": "https://api.github.com/users/elswork/orgs",
      "repos_url": "https://api.github.com/users/elswork/repos",
      "events_url": "https://api.github.com/users/elswork/events{/privacy}",
      "received_events_url": "https://api.github.com/users/elswork/received_events",
      "type": "User",
      "site_admin": false
    },
    "labels": [],
    "state": "open",
    "locked": false,
    "assignee": null,
    "assignees": [],
    "milestone": null,
    "comments": 1,
    "created_at": "2023-11-25T18:13:12Z",
    "updated_at": "2023-11-25T19:18:23Z",
    "closed_at": null,
    "author_association": "OWNER",
    "active_lock_reason": null,
    "body": "# Test\r\nEsto es una prueba. 💕\r\n\r\n![image](https://github.com/elswork/anticitera.deft.work/assets/1455507/c5bc98b0-142a-4421-9e25-ebd9417a41b2)\r\n",
    "reactions": {
      "url": "https://api.github.com/repos/elswork/anticitera.deft.work/issues/1/reactions",
      "total_count": 1,
      "+1": 0,
      "-1": 0,
      "laugh": 0,
      "hooray": 0,
      "confused": 0,
      "heart": 0,
      "rocket": 1,
      "eyes": 0
    },
    "timeline_url": "https://api.github.com/repos/elswork/anticitera.deft.work/issues/1/timeline",
    "performed_via_github_app": null,
    "state_reason": null
  }
]